{
  "type_description_msg": {
    "type_description": {
      "type_name": "std_msgs/msg/Char",
      "fields": [
        {
          "name": "data",
          "type": {
            "type_id": 3,
            "capacity": 0,
            "string_capacity": 0,
            "nested_type_name": ""
          },
          "default_value": ""
        }
      ]
    },
    "referenced_type_descriptions": []
  },
  "type_hashes": [
    {
      "type_name": "std_msgs/msg/Char",
      "hash_string": "RIHS01_3ad2d04dd29ba19d04b16659afa3ccaedd691914b02a64e82e252f2fa6a586a9"
    }
  ]
}